LICENSE
MANIFEST.in
README.rst
setup.py
home/__init__.py
home/__main__.py
home/config.py
home/exceptions.py
home/util.py
home.egg-info/PKG-INFO
home.egg-info/SOURCES.txt
home.egg-info/dependency_links.txt
home.egg-info/entry_points.txt
home.egg-info/not-zip-safe
home.egg-info/requires.txt
home.egg-info/top_level.txt
home/collect/__init__.py
home/collect/handlers.py
home/collect/loop.py
home/conf/bootstrap.sh
home/conf/config.py.sample
home/conf/nginx.conf
home/conf/supervisord.conf
home/dash/__init__.py
home/dash/admin.py
home/dash/api.py
home/dash/models.py
home/dash/web.py
home/dash/static/css/.DS_Store
home/dash/static/css/AdminLTE.css
home/dash/static/css/bootstrap.css
home/dash/static/css/bootstrap.min.css
home/dash/static/css/font-awesome.css
home/dash/static/css/font-awesome.min.css
home/dash/static/css/home.css
home/dash/static/css/ionicons.css
home/dash/static/css/ionicons.min.css
home/dash/static/css/bootstrap-slider/slider.css
home/dash/static/css/bootstrap-wysihtml5/bootstrap3-wysihtml5.css
home/dash/static/css/bootstrap-wysihtml5/bootstrap3-wysihtml5.min.css
home/dash/static/css/colorpicker/bootstrap-colorpicker.css
home/dash/static/css/colorpicker/bootstrap-colorpicker.min.css
home/dash/static/css/datatables/dataTables.bootstrap.css
home/dash/static/css/datatables/images/sort_asc.png
home/dash/static/css/datatables/images/sort_asc_disabled.png
home/dash/static/css/datatables/images/sort_both.png
home/dash/static/css/datatables/images/sort_desc.png
home/dash/static/css/datatables/images/sort_desc_disabled.png
home/dash/static/css/daterangepicker/daterangepicker-bs3.css
home/dash/static/css/fullcalendar/fullcalendar.css
home/dash/static/css/fullcalendar/fullcalendar.print.css
home/dash/static/css/iCheck/.DS_Store
home/dash/static/css/iCheck/all.css
home/dash/static/css/iCheck/flat/_all.css
home/dash/static/css/iCheck/flat/aero.css
home/dash/static/css/iCheck/flat/aero.png
home/dash/static/css/iCheck/flat/aero@2x.png
home/dash/static/css/iCheck/flat/blue.css
home/dash/static/css/iCheck/flat/blue.png
home/dash/static/css/iCheck/flat/blue@2x.png
home/dash/static/css/iCheck/flat/flat.css
home/dash/static/css/iCheck/flat/flat.png
