Metadata-Version: 1.1
Name: home
Version: 0.3.4
Summary: Home automation by @d0ugal.
Home-page: https://github.com/d0ugal/home
Author: Dougal Matthews
Author-email: dougal@dougalmatthews.com
License: BSD
Platform: any
Classifier: Development Status :: 4 - Beta
Classifier: Intended Audience :: Developers
Classifier: License :: OSI Approved :: BSD License
Classifier: Operating System :: OS Independent
Classifier: Programming Language :: Python
Classifier: Programming Language :: Python :: 3.3
Classifier: Programming Language :: Python :: 3.4
